tvguiden/__init__.py
tvguiden/tvguiden.py
tvguiden-0.0.1.dist-info/LICENSE
tvguiden-0.0.1.dist-info/METADATA
tvguiden-0.0.1.dist-info/WHEEL
tvguiden-0.0.1.dist-info/top_level.txt
tvguiden-0.0.1.dist-info/RECORD
